c7n_org/__init__.py
c7n_org/cli.py
c7n_org/utils.py
c7n_org-0.6.48.dist-info/METADATA
c7n_org-0.6.48.dist-info/WHEEL
c7n_org-0.6.48.dist-info/entry_points.txt
c7n_org-0.6.48.dist-info/RECORD
